{
  "name": "Person",
  "base": "PersistedModel",
  "idInjection": false,
  "options": {
    "validateUpsert": true
  },
  "mysql": {
    "schema": "live_events",
    "table": "person"
  },
  "properties": {
    "id": {
      "type": "Number",
      "id": true,
      "required": true,
      "length": null,
      "precision": 10,
      "scale": 0,
      "mysql": {
        "columnName": "id",
        "dataType": "int",
        "dataLength": null,
        "dataPrecision": 10,
        "dataScale": 0,
        "nullable": "N"
      },
      "_selectable": false
    },
    "firstname": {
      "type": "String",
      "required": true,
      "length": 100,
      "precision": null,
      "scale": null,
      "mysql": {
        "columnName": "firstName",
        "dataType": "varchar",
        "dataLength": 100,
        "dataPrecision": null,
        "dataScale": null,
        "nullable": "N"
      },
      "_selectable": false
    },
    "lastname": {
      "type": "String",
      "required": true,
      "length": 100,
      "precision": null,
      "scale": null,
      "mysql": {
        "columnName": "lastName",
        "dataType": "varchar",
        "dataLength": 100,
        "dataPrecision": null,
        "dataScale": null,
        "nullable": "N"
      },
      "_selectable": false
    },
    "birthdate": {
      "type": "Date",
      "required": false,
      "length": null,
      "precision": null,
      "scale": null,
      "mysql": {
        "columnName": "birthDate",
        "dataType": "datetime",
        "dataLength": null,
        "dataPrecision": null,
        "dataScale": null,
        "nullable": "Y"
      },
      "_selectable": true
    },
    "cdate": {
      "type": "Date",
      "required": false,
      "length": null,
      "precision": null,
      "scale": null,
      "mysql": {
        "columnName": "cDate",
        "dataType": "timestamp",
        "dataLength": null,
        "dataPrecision": null,
        "dataScale": null,
        "nullable": "Y"
      },
      "_selectable": true
    },
    "isteacher": {
      "type": "Number",
      "required": false,
      "length": null,
      "precision": 3,
      "scale": 0,
      "mysql": {
        "columnName": "isTeacher",
        "dataType": "tinyint",
        "dataLength": null,
        "dataPrecision": 3,
        "dataScale": 0,
        "nullable": "Y"
      },
      "_selectable": true
    },
    "isvolunteer": {
      "type": "Number",
      "required": false,
      "length": null,
      "precision": 3,
      "scale": 0,
      "mysql": {
        "columnName": "isVolunteer",
        "dataType": "tinyint",
        "dataLength": null,
        "dataPrecision": 3,
        "dataScale": 0,
        "nullable": "Y"
      },
      "_selectable": true
    },
    "ismember": {
      "type": "Number",
      "required": false,
      "length": null,
      "precision": 3,
      "scale": 0,
      "mysql": {
        "columnName": "isMember",
        "dataType": "tinyint",
        "dataLength": null,
        "dataPrecision": 3,
        "dataScale": 0,
        "nullable": "Y"
      },
      "_selectable": true
    },
    "isemployee": {
      "type": "Number",
      "required": false,
      "length": null,
      "precision": 3,
      "scale": 0,
      "mysql": {
        "columnName": "isEmployee",
        "dataType": "tinyint",
        "dataLength": null,
        "dataPrecision": 3,
        "dataScale": 0,
        "nullable": "Y"
      },
      "_selectable": true
    },
    "isrenter": {
      "type": "Number",
      "required": false,
      "length": null,
      "precision": 3,
      "scale": 0,
      "mysql": {
        "columnName": "isRenter",
        "dataType": "tinyint",
        "dataLength": null,
        "dataPrecision": 3,
        "dataScale": 0,
        "nullable": "Y"
      },
      "_selectable": true
    },
    "isuser": {
      "type": "Number",
      "required": false,
      "length": null,
      "precision": 3,
      "scale": 0,
      "mysql": {
        "columnName": "isUser",
        "dataType": "tinyint",
        "dataLength": null,
        "dataPrecision": 3,
        "dataScale": 0,
        "nullable": "Y"
      },
      "_selectable": true
    },
    "sex": {
      "type": "Number",
      "required": false,
      "length": null,
      "precision": 3,
      "scale": 0,
      "mysql": {
        "columnName": "sex",
        "dataType": "tinyint",
        "dataLength": null,
        "dataPrecision": 3,
        "dataScale": 0,
        "nullable": "Y"
      },
      "_selectable": true
    },
    "mpersonId": {
      "type": "Number",
      "required": false,
      "length": null,
      "precision": 10,
      "scale": 0,
      "mysql": {
        "columnName": "mperson_id",
        "dataType": "int",
        "dataLength": null,
        "dataPrecision": 10,
        "dataScale": 0,
        "nullable": "Y"
      },
      "_selectable": true
    },
    "content": {
      "type": "String",
      "required": false,
      "length": 1000,
      "precision": null,
      "scale": null,
      "mysql": {
        "columnName": "content",
        "dataType": "varchar",
        "dataLength": 1000,
        "dataPrecision": null,
        "dataScale": null,
        "nullable": "Y"
      },
      "_selectable": true
    }
  },
  "validations": [],
  "relations": {
    "edu": {
      "type": "hasMany",
      "model": "PEdu",
      "foreignKey": ""
    },
    "emp": {
      "type": "hasMany",
      "model": "PEmp",
      "foreignKey": ""
    },
    "phones": {
      "type": "hasMany",
      "model": "PPhone",
      "foreignKey": ""
    },
    "emails": {
      "type": "hasMany",
      "model": "PEmail",
      "foreignKey": ""
    },
    "citi": {
      "type": "hasMany",
      "model": "PCiti",
      "foreignKey": ""
    },
    "addss": {
      "type": "hasMany",
      "model": "VPaddress",
      "foreignKey": ""
    },
    "stats": {
      "type": "hasMany",
      "model": "PStat",
      "foreignKey": ""
    },
    "statements": {
      "type": "hasMany",
      "model": "Statement",
      "foreignKey": "personId",
      "through": "PStat"
    }
  },
  "acls": [],
  "methods": {}
}